Workbook
Name TotalMonthlyExpenses: #REF!
Name TotalMonthlyIncome: #REF!
Name TotalMonthlySavings: #REF!

Sheet BV
E2: BANK VOUCHER
B3: داخلي | Internal
B4: Voucher : NO | E4: 2024-814 | J4: القسيمة :
B5: Date: | E5: 45615 | J5: التاريخ :
B6: Mode Of Payment : | E6: Online Transfer | J6: طريقة الصرف :
B7: Department : | E7: Procurement Department (PO) | J7: القسم :
B9: بيانات المستفيد | Beneficiary information
B10: Bank Details : | E10: Al Rajhi Bank (RJHI) | J10: التفاصيل البنكية:
B11: Remit To : | E11: Gulfwest Company Limited-0040 | J11: تحويل الى :
B12: IBAN : | E12: SA9480000425608010205547
B13: VAT DETAILS | E13: VAT NO:----------------------------- | F13: NAME OF SUPPLIER------------------ | G13: INVOICE NO ------------------ | H13: INVOICE DATE | J13: التفاصيل البنكية:
B14: PREPAYMENT DETAILS | E14: PERIOD | F14: 01-11-2024 TO 31-10-2025 | H14: AMORTIZATION PERIOD | I14: 12 MONTHS
B15: COST CENTRE DETAILS | E15: Turkey Square
B16: DESCRIPTION | E16: SUPPLY OF MILK AND YOGURT
B18: تفاصيل الدفع | Payment details
B19: Budgeted Amount. | E19: Difference | F19: Total Spent Amount | H19: Marble CO. Bank | J19: Remarks
B20: 682947.28 | E20: 66899.272 | F20: 616048.01 | H20: Al Rajhi Bank (RJHI) , (SA8580000609608010000763)
B21: Amount : | E21: 452408.9 | J21: المبلغ :
B23: CEO | E23: Procurement Department (PO) | J23: Finance Department
E24: Procurement Manager | J24: Accounting Manager

Sheet Bill details
E2: BANK VOUCHER
B3: داخلي | Internal
B4: Voucher : NO | E4: 2024-814 | J4: القسيمة :
B5: Date: | E5: 45615 | J5: التاريخ :
B6: Mode Of Payment : | E6: Online Transfer | J6: طريقة الصرف :
B7: Department : | E7: Procurement Department (PO) | J7: القسم :
B9: بيانات المستفيد | Beneficiary information
B10: Bank Details : | E10: Al Rajhi Bank (RJHI) | J10: التفاصيل البنكية:
B11: Remit To : | E11: Gulfwest Company Limited-0040 | J11: تحويل الى :
B12: IBAN : | E12: SA9480000425608010205547
B13: VAT DETAILS | E13: VAT NO:----------------------------- | F13: NAME OF SUPPLIER------------------ | G13: INVOICE NO ------------------ | H13: INVOICE DATE | J13: التفاصيل البنكية:
B14: ITEM DETAILS | E14: ITEM NAME | F14: Unit of Measure | G14: QTY | H14: PRICE | I14: AMOUNT | J14: تحويل الى :
B15: PREPAYMENT DETAILS | E15: PERIOD | F15: 01-11-2024 TO 31-10-2025 | H15: AMORTIZATION PERIOD | I15: 12 MONTHS
B16: COST CENTRE DETAILS | E16: Turkey Square
B17: DESCRIPTION | E17: SUPPLY OF MILK AND YOGURT
B19: تفاصيل الدفع | Payment details
B20: Budgeted Amount. | E20: Difference | F20: Total Spent Amount | H20: Marble CO. Bank | J20: Remarks
B21: 682947.28 | E21: 66899.272 | F21: 616048.01 | H21: Al Rajhi Bank (RJHI) , (SA8580000609608010000763)
B22: Amount : | E22: 452408.9 | J22: المبلغ :
B23: For : | E23: INVOICE OCT-2024 | J23: الغرض :
B24: Descripton | E24: SUPPLY OF MEAT | J24: دفعة :
B26: Comments | J26: تعليقات
B28: CEO | E28: Procurement Department (PO) | J28: Finance Department
E29: Procurement Manager | J29: Accounting Manager

Sheet JV
E2: JOURNAL VOUCHER
B3: داخلي | Internal
B4: Voucher : NO | E4: 2024-814 | J4: القسيمة :
B5: Date: | E5: 45615 | J5: التاريخ :
B6: Department : | E6: Procurement Department (PO) | J6: القسم :
B7: CREDIT TO : | E7: PETTY CASH-PROCUREMENT | J7: القسم :
B9: بيانات المستفيد | Beneficiary information
B10: VAT DETAILS | E10: NAME OF SUPPLIER------------------ | F10: INVOICE NO ------------- | G10: INVOICE DATE----- | H10: REGION | I10: VAT NO:----------------------------- | J10: التفاصيل البنكية:
B11: PREPAYMENT DETAILS | E11: PERIOD | F11: 45302 | G11: 31-10-2025 | H11: AMORTIZATION PERIOD | I11: 12 MONTHS
B12: COST CENTRE DETAILS | E12: TURKEY SQUARE
B13: DESCRIPTION | E13: SUPPLY OF MILK AND YOGURT
B15: تفاصيل الدفع | Payment details
B16: Budgeted Amount. | E16: Difference | F16: Total Spent Amount in a Year | J16: Remarks
B17: 1000000 | E17: 25000 | F17: 75000
B19: التوجيه المحاسبي | Accounting guidance
B20: B.U | D20: Expense Category | G20: Expense Head | J20: Dr. | K20: Cr.
B22: CEO | E22: Procurement Department (PO) | J22: Finance Department
E23: Procurement Manager | J23: Accounting Manager

Sheet Sheet5
A1: =#REF! -> #REF! | B1: Procurement Department (PO) | C1: Human Resources Department (HR) | D1: Information Technology Department (IT) | E1: Marketing Department (MKT) | F1: Operation Department (OP) | G1: Maintenance (OP-M) | H1: Customer Care (MKT-CC) | I1: Finance (FIN) | J1: Admin
A2: =#REF! -> #REF! | B2: =INDEX(#REF!,MATCH(BV!$E$4,#REF!,0),MATCH(#REF!,#REF!,0)) -> #REF! | C2: =INDEX(#REF!,MATCH(BV!$E$4,#REF!,0),MATCH(#REF!,#REF!,0)) -> #REF! | D2: =INDEX(#REF!,MATCH(BV!$E$4,#REF!,0),MATCH(#REF!,#REF!,0)) -> #REF! | E2: =INDEX(#REF!,MATCH(Sheet5!E1,#REF!,0),MATCH(Sheet5!$A$1,#REF!,0)) -> #REF! | F2: =INDEX(#REF!,MATCH(Sheet5!F1,#REF!,0),MATCH(Sheet5!$A$1,#REF!,0)) -> #REF! | G2: =INDEX(#REF!,MATCH(Sheet5!G1,#REF!,0),MATCH(Sheet5!$A$1,#REF!,0)) -> #REF! | H2: =INDEX(#REF!,MATCH(Sheet5!H1,#REF!,0),MATCH(Sheet5!$A$1,#REF!,0)) -> #REF! | I2: =INDEX(#REF!,MATCH(Sheet5!I1,#REF!,0),MATCH(Sheet5!$A$1,#REF!,0)) -> #REF! | J2: =INDEX(#REF!,MATCH(Sheet5!J1,#REF!,0),MATCH(Sheet5!$A$1,#REF!,0)) -> #REF!
A3: =#REF! -> #REF! | B3: =INDEX(#REF!,MATCH(Sheet5!B2,#REF!,0),MATCH(Sheet5!$A$1,#REF!,0)) -> #REF! | C3: =INDEX(#REF!,MATCH(Sheet5!C2,#REF!,0),MATCH(Sheet5!$A$1,#REF!,0)) -> #REF! | D3: =INDEX(#REF!,MATCH(Sheet5!D2,#REF!,0),MATCH(Sheet5!$A$1,#REF!,0)) -> #REF! | E3: =INDEX(#REF!,MATCH(Sheet5!E2,#REF!,0),MATCH(Sheet5!$A$1,#REF!,0)) -> #REF! | F3: =INDEX(#REF!,MATCH(Sheet5!F2,#REF!,0),MATCH(Sheet5!$A$1,#REF!,0)) -> #REF! | G3: =INDEX(#REF!,MATCH(Sheet5!G2,#REF!,0),MATCH(Sheet5!$A$1,#REF!,0)) -> #REF! | H3: =INDEX(#REF!,MATCH(Sheet5!H2,#REF!,0),MATCH(Sheet5!$A$1,#REF!,0)) -> #REF! | I3: =INDEX(#REF!,MATCH(Sheet5!I2,#REF!,0),MATCH(Sheet5!$A$1,#REF!,0)) -> #REF! | J3: =INDEX(#REF!,MATCH(Sheet5!J2,#REF!,0),MATCH(Sheet5!$A$1,#REF!,0)) -> #REF!
A4: =#REF! -> #REF! | B4: =INDEX(#REF!,MATCH(Sheet5!B3,#REF!,0),MATCH(Sheet5!$A$1,#REF!,0)) -> #REF! | C4: =INDEX(#REF!,MATCH(Sheet5!C3,#REF!,0),MATCH(Sheet5!$A$1,#REF!,0)) -> #REF! | D4: =INDEX(#REF!,MATCH(Sheet5!D3,#REF!,0),MATCH(Sheet5!$A$1,#REF!,0)) -> #REF! | E4: =INDEX(#REF!,MATCH(Sheet5!E3,#REF!,0),MATCH(Sheet5!$A$1,#REF!,0)) -> #REF! | F4: =INDEX(#REF!,MATCH(Sheet5!F3,#REF!,0),MATCH(Sheet5!$A$1,#REF!,0)) -> #REF! | G4: =INDEX(#REF!,MATCH(Sheet5!G3,#REF!,0),MATCH(Sheet5!$A$1,#REF!,0)) -> #REF! | H4: =INDEX(#REF!,MATCH(Sheet5!H3,#REF!,0),MATCH(Sheet5!$A$1,#REF!,0)) -> #REF! | I4: =INDEX(#REF!,MATCH(Sheet5!I3,#REF!,0),MATCH(Sheet5!$A$1,#REF!,0)) -> #REF! | J4: =INDEX(#REF!,MATCH(Sheet5!J3,#REF!,0),MATCH(Sheet5!$A$1,#REF!,0)) -> #REF!
A5: =#REF! -> #REF! | B5: =INDEX(#REF!,MATCH(Sheet5!B4,#REF!,0),MATCH(Sheet5!$A$1,#REF!,0)) -> #REF! | C5: =INDEX(#REF!,MATCH(Sheet5!C4,#REF!,0),MATCH(Sheet5!$A$1,#REF!,0)) -> #REF! | D5: =INDEX(#REF!,MATCH(Sheet5!D4,#REF!,0),MATCH(Sheet5!$A$1,#REF!,0)) -> #REF! | E5: =INDEX(#REF!,MATCH(Sheet5!E4,#REF!,0),MATCH(Sheet5!$A$1,#REF!,0)) -> #REF! | F5: =INDEX(#REF!,MATCH(Sheet5!F4,#REF!,0),MATCH(Sheet5!$A$1,#REF!,0)) -> #REF! | G5: =INDEX(#REF!,MATCH(Sheet5!G4,#REF!,0),MATCH(Sheet5!$A$1,#REF!,0)) -> #REF! | H5: =INDEX(#REF!,MATCH(Sheet5!H4,#REF!,0),MATCH(Sheet5!$A$1,#REF!,0)) -> #REF! | I5: =INDEX(#REF!,MATCH(Sheet5!I4,#REF!,0),MATCH(Sheet5!$A$1,#REF!,0)) -> #REF! | J5: =INDEX(#REF!,MATCH(Sheet5!J4,#REF!,0),MATCH(Sheet5!$A$1,#REF!,0)) -> #REF!
A6: =#REF! -> #REF! | B6: =INDEX(#REF!,MATCH(Sheet5!B5,#REF!,0),MATCH(Sheet5!$A$1,#REF!,0)) -> #REF! | C6: =INDEX(#REF!,MATCH(Sheet5!C5,#REF!,0),MATCH(Sheet5!$A$1,#REF!,0)) -> #REF! | D6: =INDEX(#REF!,MATCH(Sheet5!D5,#REF!,0),MATCH(Sheet5!$A$1,#REF!,0)) -> #REF! | E6: =INDEX(#REF!,MATCH(Sheet5!E5,#REF!,0),MATCH(Sheet5!$A$1,#REF!,0)) -> #REF! | F6: =INDEX(#REF!,MATCH(Sheet5!F5,#REF!,0),MATCH(Sheet5!$A$1,#REF!,0)) -> #REF! | G6: =INDEX(#REF!,MATCH(Sheet5!G5,#REF!,0),MATCH(Sheet5!$A$1,#REF!,0)) -> #REF! | H6: =INDEX(#REF!,MATCH(Sheet5!H5,#REF!,0),MATCH(Sheet5!$A$1,#REF!,0)) -> #REF! | I6: =INDEX(#REF!,MATCH(Sheet5!I5,#REF!,0),MATCH(Sheet5!$A$1,#REF!,0)) -> #REF! | J6: =INDEX(#REF!,MATCH(Sheet5!J5,#REF!,0),MATCH(Sheet5!$A$1,#REF!,0)) -> #REF!
A7: =#REF! -> #REF! | B7: =INDEX(#REF!,MATCH(Sheet5!B6,#REF!,0),MATCH(Sheet5!$A$1,#REF!,0)) -> #REF! | C7: =INDEX(#REF!,MATCH(Sheet5!C6,#REF!,0),MATCH(Sheet5!$A$1,#REF!,0)) -> #REF! | D7: =INDEX(#REF!,MATCH(Sheet5!D6,#REF!,0),MATCH(Sheet5!$A$1,#REF!,0)) -> #REF! | E7: =INDEX(#REF!,MATCH(Sheet5!E6,#REF!,0),MATCH(Sheet5!$A$1,#REF!,0)) -> #REF! | F7: =INDEX(#REF!,MATCH(Sheet5!F6,#REF!,0),MATCH(Sheet5!$A$1,#REF!,0)) -> #REF! | G7: =INDEX(#REF!,MATCH(Sheet5!G6,#REF!,0),MATCH(Sheet5!$A$1,#REF!,0)) -> #REF! | H7: =INDEX(#REF!,MATCH(Sheet5!H6,#REF!,0),MATCH(Sheet5!$A$1,#REF!,0)) -> #REF! | I7: =INDEX(#REF!,MATCH(Sheet5!I6,#REF!,0),MATCH(Sheet5!$A$1,#REF!,0)) -> #REF! | J7: =INDEX(#REF!,MATCH(Sheet5!J6,#REF!,0),MATCH(Sheet5!$A$1,#REF!,0)) -> #REF!
A8: =#REF! -> #REF! | B8: =INDEX(#REF!,MATCH(Sheet5!B7,#REF!,0),MATCH(Sheet5!$A$1,#REF!,0)) -> #REF! | C8: =INDEX(#REF!,MATCH(Sheet5!C7,#REF!,0),MATCH(Sheet5!$A$1,#REF!,0)) -> #REF! | D8: =INDEX(#REF!,MATCH(Sheet5!D7,#REF!,0),MATCH(Sheet5!$A$1,#REF!,0)) -> #REF! | E8: =INDEX(#REF!,MATCH(Sheet5!E7,#REF!,0),MATCH(Sheet5!$A$1,#REF!,0)) -> #REF! | F8: =INDEX(#REF!,MATCH(Sheet5!F7,#REF!,0),MATCH(Sheet5!$A$1,#REF!,0)) -> #REF! | G8: =INDEX(#REF!,MATCH(Sheet5!G7,#REF!,0),MATCH(Sheet5!$A$1,#REF!,0)) -> #REF! | H8: =INDEX(#REF!,MATCH(Sheet5!H7,#REF!,0),MATCH(Sheet5!$A$1,#REF!,0)) -> #REF! | I8: =INDEX(#REF!,MATCH(Sheet5!I7,#REF!,0),MATCH(Sheet5!$A$1,#REF!,0)) -> #REF! | J8: =INDEX(#REF!,MATCH(Sheet5!J7,#REF!,0),MATCH(Sheet5!$A$1,#REF!,0)) -> #REF!
A9: =#REF! -> #REF! | B9: =INDEX(#REF!,MATCH(Sheet5!B8,#REF!,0),MATCH(Sheet5!$A$1,#REF!,0)) -> #REF! | C9: =INDEX(#REF!,MATCH(Sheet5!C8,#REF!,0),MATCH(Sheet5!$A$1,#REF!,0)) -> #REF! | D9: =INDEX(#REF!,MATCH(Sheet5!D8,#REF!,0),MATCH(Sheet5!$A$1,#REF!,0)) -> #REF! | E9: =INDEX(#REF!,MATCH(Sheet5!E8,#REF!,0),MATCH(Sheet5!$A$1,#REF!,0)) -> #REF! | F9: =INDEX(#REF!,MATCH(Sheet5!F8,#REF!,0),MATCH(Sheet5!$A$1,#REF!,0)) -> #REF! | G9: =INDEX(#REF!,MATCH(Sheet5!G8,#REF!,0),MATCH(Sheet5!$A$1,#REF!,0)) -> #REF! | H9: =INDEX(#REF!,MATCH(Sheet5!H8,#REF!,0),MATCH(Sheet5!$A$1,#REF!,0)) -> #REF! | I9: =INDEX(#REF!,MATCH(Sheet5!I8,#REF!,0),MATCH(Sheet5!$A$1,#REF!,0)) -> #REF! | J9: =INDEX(#REF!,MATCH(Sheet5!J8,#REF!,0),MATCH(Sheet5!$A$1,#REF!,0)) -> #REF!
A10: =#REF! -> #REF! | B10: =INDEX(#REF!,MATCH(Sheet5!B9,#REF!,0),MATCH(Sheet5!$A$1,#REF!,0)) -> #REF! | C10: =INDEX(#REF!,MATCH(Sheet5!C9,#REF!,0),MATCH(Sheet5!$A$1,#REF!,0)) -> #REF! | D10: =INDEX(#REF!,MATCH(Sheet5!D9,#REF!,0),MATCH(Sheet5!$A$1,#REF!,0)) -> #REF! | E10: =INDEX(#REF!,MATCH(Sheet5!E9,#REF!,0),MATCH(Sheet5!$A$1,#REF!,0)) -> #REF! | F10: =INDEX(#REF!,MATCH(Sheet5!F9,#REF!,0),MATCH(Sheet5!$A$1,#REF!,0)) -> #REF! | G10: =INDEX(#REF!,MATCH(Sheet5!G9,#REF!,0),MATCH(Sheet5!$A$1,#REF!,0)) -> #REF! | H10: =INDEX(#REF!,MATCH(Sheet5!H9,#REF!,0),MATCH(Sheet5!$A$1,#REF!,0)) -> #REF! | I10: =INDEX(#REF!,MATCH(Sheet5!I9,#REF!,0),MATCH(Sheet5!$A$1,#REF!,0)) -> #REF! | J10: =INDEX(#REF!,MATCH(Sheet5!J9,#REF!,0),MATCH(Sheet5!$A$1,#REF!,0)) -> #REF!
A11: =#REF! -> #REF! | B11: =INDEX(#REF!,MATCH(Sheet5!B10,#REF!,0),MATCH(Sheet5!$A$1,#REF!,0)) -> #REF! | C11: =INDEX(#REF!,MATCH(Sheet5!C10,#REF!,0),MATCH(Sheet5!$A$1,#REF!,0)) -> #REF! | D11: =INDEX(#REF!,MATCH(Sheet5!D10,#REF!,0),MATCH(Sheet5!$A$1,#REF!,0)) -> #REF! | E11: =INDEX(#REF!,MATCH(Sheet5!E10,#REF!,0),MATCH(Sheet5!$A$1,#REF!,0)) -> #REF! | F11: =INDEX(#REF!,MATCH(Sheet5!F10,#REF!,0),MATCH(Sheet5!$A$1,#REF!,0)) -> #REF! | G11: =INDEX(#REF!,MATCH(Sheet5!G10,#REF!,0),MATCH(Sheet5!$A$1,#REF!,0)) -> #REF! | H11: =INDEX(#REF!,MATCH(Sheet5!H10,#REF!,0),MATCH(Sheet5!$A$1,#REF!,0)) -> #REF! | I11: =INDEX(#REF!,MATCH(Sheet5!I10,#REF!,0),MATCH(Sheet5!$A$1,#REF!,0)) -> #REF! | J11: =INDEX(#REF!,MATCH(Sheet5!J10,#REF!,0),MATCH(Sheet5!$A$1,#REF!,0)) -> #REF!
A12: =#REF! -> #REF! | B12: =INDEX(#REF!,MATCH(Sheet5!B11,#REF!,0),MATCH(Sheet5!$A$1,#REF!,0)) -> #REF! | C12: =INDEX(#REF!,MATCH(Sheet5!C11,#REF!,0),MATCH(Sheet5!$A$1,#REF!,0)) -> #REF! | D12: =INDEX(#REF!,MATCH(Sheet5!D11,#REF!,0),MATCH(Sheet5!$A$1,#REF!,0)) -> #REF! | E12: =INDEX(#REF!,MATCH(Sheet5!E11,#REF!,0),MATCH(Sheet5!$A$1,#REF!,0)) -> #REF! | F12: =INDEX(#REF!,MATCH(Sheet5!F11,#REF!,0),MATCH(Sheet5!$A$1,#REF!,0)) -> #REF! | G12: =INDEX(#REF!,MATCH(Sheet5!G11,#REF!,0),MATCH(Sheet5!$A$1,#REF!,0)) -> #REF! | H12: =INDEX(#REF!,MATCH(Sheet5!H11,#REF!,0),MATCH(Sheet5!$A$1,#REF!,0)) -> #REF! | I12: =INDEX(#REF!,MATCH(Sheet5!I11,#REF!,0),MATCH(Sheet5!$A$1,#REF!,0)) -> #REF! | J12: =INDEX(#REF!,MATCH(Sheet5!J11,#REF!,0),MATCH(Sheet5!$A$1,#REF!,0)) -> #REF!
A13: =#REF! -> #REF! | B13: =INDEX(#REF!,MATCH(Sheet5!B12,#REF!,0),MATCH(Sheet5!$A$1,#REF!,0)) -> #REF! | C13: =INDEX(#REF!,MATCH(Sheet5!C12,#REF!,0),MATCH(Sheet5!$A$1,#REF!,0)) -> #REF! | D13: =INDEX(#REF!,MATCH(Sheet5!D12,#REF!,0),MATCH(Sheet5!$A$1,#REF!,0)) -> #REF! | E13: =INDEX(#REF!,MATCH(Sheet5!E12,#REF!,0),MATCH(Sheet5!$A$1,#REF!,0)) -> #REF! | F13: =INDEX(#REF!,MATCH(Sheet5!F12,#REF!,0),MATCH(Sheet5!$A$1,#REF!,0)) -> #REF! | G13: =INDEX(#REF!,MATCH(Sheet5!G12,#REF!,0),MATCH(Sheet5!$A$1,#REF!,0)) -> #REF! | H13: =INDEX(#REF!,MATCH(Sheet5!H12,#REF!,0),MATCH(Sheet5!$A$1,#REF!,0)) -> #REF! | I13: =INDEX(#REF!,MATCH(Sheet5!I12,#REF!,0),MATCH(Sheet5!$A$1,#REF!,0)) -> #REF! | J13: =INDEX(#REF!,MATCH(Sheet5!J12,#REF!,0),MATCH(Sheet5!$A$1,#REF!,0)) -> #REF!
A14: =#REF! -> #REF! | B14: =INDEX(#REF!,MATCH(Sheet5!B13,#REF!,0),MATCH(Sheet5!$A$1,#REF!,0)) -> #REF! | C14: =INDEX(#REF!,MATCH(Sheet5!C13,#REF!,0),MATCH(Sheet5!$A$1,#REF!,0)) -> #REF! | D14: =INDEX(#REF!,MATCH(Sheet5!D13,#REF!,0),MATCH(Sheet5!$A$1,#REF!,0)) -> #REF! | E14: =INDEX(#REF!,MATCH(Sheet5!E13,#REF!,0),MATCH(Sheet5!$A$1,#REF!,0)) -> #REF! | F14: =INDEX(#REF!,MATCH(Sheet5!F13,#REF!,0),MATCH(Sheet5!$A$1,#REF!,0)) -> #REF! | G14: =INDEX(#REF!,MATCH(Sheet5!G13,#REF!,0),MATCH(Sheet5!$A$1,#REF!,0)) -> #REF! | H14: =INDEX(#REF!,MATCH(Sheet5!H13,#REF!,0),MATCH(Sheet5!$A$1,#REF!,0)) -> #REF! | I14: =INDEX(#REF!,MATCH(Sheet5!I13,#REF!,0),MATCH(Sheet5!$A$1,#REF!,0)) -> #REF! | J14: =INDEX(#REF!,MATCH(Sheet5!J13,#REF!,0),MATCH(Sheet5!$A$1,#REF!,0)) -> #REF!
... A517: =#REF! -> #REF! | B517: =INDEX(#REF!,MATCH(Sheet5!B516,#REF!,0),MATCH(Sheet5!$A$1,#REF!,0)) -> #REF! | C517: =INDEX(#REF!,MATCH(Sheet5!C516,#REF!,0),MATCH(Sheet5!$A$1,#REF!,0)) -> #REF! | D517: =INDEX(#REF!,MATCH(Sheet5!D516,#REF!,0),MATCH(Sheet5!$A$1,#REF!,0)) -> #REF! | E517: =INDEX(#REF!,MATCH(Sheet5!E516,#REF!,0),MATCH(Sheet5!$A$1,#REF!,0)) -> #REF! | F517: =INDEX(#REF!,MATCH(Sheet5!F516,#REF!,0),MATCH(Sheet5!$A$1,#REF!,0)) -> #REF! | G517: =INDEX(#REF!,MATCH(Sheet5!G516,#REF!,0),MATCH(Sheet5!$A$1,#REF!,0)) -> #REF! | H517: =INDEX(#REF!,MATCH(Sheet5!H516,#REF!,0),MATCH(Sheet5!$A$1,#REF!,0)) -> #REF! | I517: =INDEX(#REF!,MATCH(Sheet5!I516,#REF!,0),MATCH(Sheet5!$A$1,#REF!,0)) -> #REF! | J517: =INDEX(#REF!,MATCH(Sheet5!J516,#REF!,0),MATCH(Sheet5!$A$1,#REF!,0)) -> #REF!
A518: =#REF! -> #REF!
A519: =#REF! -> #REF!
A520: =#REF! -> #REF!
A521: =#REF! -> #REF!
A522: =#REF! -> #REF!
A523: =#REF! -> #REF!
A524: =#REF! -> #REF!
A525: =#REF! -> #REF!
A526: =#REF! -> #REF!
A527: =#REF! -> #REF!
A528: =#REF! -> #REF!
A529: =#REF! -> #REF!
... A10836: =#REF! -> #REF!
